mapf_util/__init__.py
mapf_util/astar.py
mapf_util/compact_location.py
mapf_util/maze.py
mapf_util/node.py
mapf_util-0.0.1.dist-info/LICENSE
mapf_util-0.0.1.dist-info/METADATA
mapf_util-0.0.1.dist-info/WHEEL
mapf_util-0.0.1.dist-info/top_level.txt
mapf_util-0.0.1.dist-info/RECORD
