Metadata-Version: 2.1
Name: mapf-util
Version: 0.0.1
Summary: MAPF utility classes used by other packages
Home-page: https://github.com/tbvanderwoude/mapf-util
Author: Thom van der Woude
Author-email: tbvanderwoude@student.tudelft.nl
License: UNKNOWN
Project-URL: Bug Tracker, https://github.com/tbvanderwoude/mapf-util/issues
Platform: UNKNOWN
Classifier: Programming Language :: Python :: 3
Classifier: License :: OSI Approved :: MIT License
Classifier: Operating System :: OS Independent
Requires-Python: >=3.9
License-File: LICENSE
